{
    "manifest": {
        "version": "1.0",
        "author": "cbani",
        "name": "TokyoNight",
        "updater": "https:\/\/raw.githubusercontent.com\/rennpy\/TokyoNight\/main\/TokyoNight.json"
    },
    "background": {},
    "fonts": {
        "ginto_bold": "https:\/\/github.com\/rennpy\/TokyoNight\/raw\/main\/CascadiaCode-Bold.ttf",
        "whitney_bold": "https:\/\/github.com\/rennpy\/TokyoNight\/raw\/main\/CascadiaCode-Bold.ttf",
        "ginto_regular": "https:\/\/github.com\/rennpy\/TokyoNight\/raw\/main\/CascadiaCode-Regular.ttf",
        "ginto_medium": "https:\/\/github.com\/rennpy\/TokyoNight\/raw\/main\/CascadiaCode-SemiBold.ttf",
        "whitney_semibold": "https:\/\/github.com\/rennpy\/TokyoNight\/raw\/main\/CascadiaCode-SemiBold.ttf",
        "whitney_medium": "https:\/\/github.com\/rennpy\/TokyoNight\/raw\/main\/CascadiaCode-Regular.ttf"
    },
    "simple_colors": {
        "mention_highlight": 681496170,
        "accent": -6369686,
        "input_background": -14276295,
        "active_channel": -13618360
    },
    "colors": {
        "link": -6369686,
        "primary_700": -14276295,
        "primary_dark_360": -10985858,
        "primary_dark_400": -10123418,
        "primary_dark_600": -15066330,
        "primary_dark_630": -14276295,
        "primary_dark_660": -15066330,
        "primary_dark_700": -15066330,
        "primary_dark_800": -14276295,
        "uikit_btn_bg_color_selector_red": -4234902,
        "uikit_btn_compound_color_selector_light": -10985858,
        "primary_dark_300": -12959909,
        "uikit_btn_bg_color_selector_green": -6703508,
        "primary_dark_200": -7105370,
        "uikit_btn_compound_color_selector_dark": -10985858,
        "brand_500_alpha_20": -1180774806,
        "uikit_settings_item_text_color_dark": -2564375,
        "uikit_settings_item_text_color_light": -14276295,
        "link_500": -6369686,
        "brand_new_560": 2435380,
        "primary_700_alpha_60": -6369686,
        "black_alpha_10": 3811899,
        "primary_dark_900": -16777216,
        "primary_900_alpha_80": -13158858,
        "primary_660": -6369686,
        "primary_630": -14276295,
        "primary_dark_330": -10985858,
        "brand_new_500": 1839124074,
        "primary_300": -10985858,
        "white_500": -7105370,
        "brand_260": -6369686,
        "brand_500": -6369686,
        "brand_900": -6369686,
        "brand_new_230": -6369686,
        "brand_new_260": -6369686,
        "brand_new_330": -6369686,
        "primary_dark_100": -14276295
    },
    "drawable_tints": {
        "drawable_overlay_channels_selected_dark": -15066330,
        "ic_channel_text": -10985858,
        "ic_sidebar_pins_off_dark_24dp": -10985858,
        "ic_sidebar_notifications_on_dark_24dp": -10985858,
        "ic_sidebar_notifications_off_dark_24dp": -10985858,
        "drawable_voice_indicator_speaking": -4234902,
        "drawable_overlay_channels_dark": -14276295,
        "ic_direct_message_header": -14276295,
        "ic_group_message_header": -14276295,
        "ic_menu_24dp": -10985858,
        "ic_channel_announcements": -10985858,
        "ic_channel_announcements_locked": -10985858,
        "ic_channel_announcements_nsfw": -10985858,
        "ic_channel_text_locked": -10985858,
        "ic_channel_text_nsfw": -10985858,
        "ic_thread": -14276295,
        "ic_thread_nsfw": -14276295,
        "ic_thread_locked": -14276295,
        "ic_channel_topic_ellipsis_light": -10985858,
        "ic_channel_topic_ellipsis_dark": -10985858,
        "ic_channel_voice_locked": -10985858,
        "ic_channel_voice": -10985858,
        "ic_channel_lock_16dp": -10985858,
        "ic_channel_announcements_thread_nsfw": -10985858,
        "ic_channel_announcements_thread_locked": -10985858,
        "ic_channel_announcements_thread": -10985858,
        "ic_channel_pinned_message": -10985858,
        "ic_sidebar_search_24dp": -10985858,
        "ic_open_in_browser_white_24dp": -10985858,
        "ic_file_download_white_24dp": -6703508,
        "ic_share_white_24dp": -10387102,
        "ic_arrow_back_white_24dp": -10985858,
        "ic_archived_clock_dark": -10985858,
        "ic_notifications_white_a60_24dp": -10985858,
        "ic_visibility_white_24dp": -10985858,
        "ic_thread_white_24dp": -10985858,
        "ic_content_copy_white_a60_24dp": -10985858,
        "ic_notifications_settings_white_a60_24dp": -10985858,
        "ic_person_add_white_a60_24dp": -10985858,
        "ic_settings_white_a60_24dp": -10985858,
        "ic_notifications_off_white_a60_24dp": -10985858,
        "ic_share_white_a60_24dp": -10985858,
        "ic_open_in_new_white_a60_24dp": -10985858,
        "ic_account_circle_white_a60_24dp": -10985858,
        "drawable_open_folder_dark": -14276295
    },
    "raws": {}
}